{
"Parameters": {
	"Power balance penalty ($/MW)": [10000.0, 10000.0, 10000.0, 10000.0, 10000.0, 10000.0, 10000.0, 10000.0, 10000.0, 10000.0, 10000.0, 10000.0, 10000.0, 10000.0, 10000.0, 10000.0, 10000.0, 10000.0, 10000.0, 10000.0, 10000.0, 10000.0, 10000.0, 10000.0, 10000.0, 10000.0, 10000.0, 10000.0, 10000.0, 10000.0, 10000.0, 10000.0, 10000.0, 10000.0, 10000.0, 10000.0, 10000.0, 10000.0, 10000.0, 10000.0, 10000.0, 10000.0, 10000.0, 10000.0, 10000.0, 10000.0, 10000.0, 10000.0, 10000.0, 10000.0, 10000.0, 10000.0, 10000.0, 10000.0, 10000.0, 10000.0, 10000.0, 10000.0, 10000.0, 10000.0, 10000.0, 10000.0, 10000.0, 10000.0, 10000.0, 10000.0, 10000.0, 10000.0, 10000.0, 10000.0, 10000.0, 10000.0, 10000.0, 10000.0, 10000.0, 10000.0, 10000.0, 10000.0, 10000.0, 10000.0, 10000.0, 10000.0, 10000.0, 10000.0, 10000.0, 10000.0, 10000.0, 10000.0, 10000.0, 10000.0, 10000.0, 10000.0, 10000.0, 10000.0, 10000.0, 10000.0],
	"Scenario number": 1,
	"Time horizon (h)": 12,
	"Time step (min)": 15},
	"Generators": {
		"g1": {
			"Bus": "b1",
			"Production cost curve (MW)": [16.901100444445653, 94.40345818607902, 171.90581592771244, 249.40817366934598, 326.91053141097933],
			"Production cost curve ($)": [716.7470233305867, 3465.763907745978, 6335.568940853531, 9252.345705326847, 12232.933634581022],
			"Startup costs ($)": [20559.35, 24224.12, 28727.63],
			"Startup delays (h)": [1.0, 2.0, 4.0],
			"Ramp up limit (MW)": 57.21,
			"Ramp down limit (MW)": 57.21,
			"Startup limit (MW)": 228.84,
			"Shutdown limit (MW)": 228.84,
			"Minimum uptime (h)": 1,
			"Minimum downtime (h)": 1,
			"Initial status (h)": 24,
			"Initial power (MW)": 257.74170000000004
		},
		"g2": {
			"Bus": "b2",
			"Production cost curve (MW)": [2.257203830814138, 33.5985679204243, 64.93993201003447, 96.28129609964463, 127.62266018925479],
			"Production cost curve ($)": [953.4271497797719, 2139.086577758979, 3416.0435375709003, 4856.980529832745, 6523.928912640124],
			"Startup costs ($)": [10345.29, 10498.58, 10598.13],
			"Startup delays (h)": [1.0, 2.0, 4.0],
			"Ramp up limit (MW)": 22.335,
			"Ramp down limit (MW)": 22.335,
			"Startup limit (MW)": 89.34,
			"Shutdown limit (MW)": 89.34,
			"Minimum uptime (h)": 1,
			"Minimum downtime (h)": 1,
			"Initial status (h)": -24,
			"Initial power (MW)": 0.0
		},
		"g3": {
			"Bus": "b3",
			"Production cost curve (MW)": [1.619043590917833, 21.894126410542157, 42.16920923016648, 62.444292049790796, 82.71937486941513],
			"Production cost curve ($)": [685.7745024725275, 1403.8176490424148, 2365.8595550594155, 3786.959826482599, 5342.322597393779],
			"Startup costs ($)": [4382.12, 4505.39, 4595.43],
			"Startup delays (h)": [1.0, 2.0, 4.0],
			"Ramp up limit (MW)": 14.475,
			"Ramp down limit (MW)": 14.475,
			"Startup limit (MW)": 57.9,
			"Shutdown limit (MW)": 57.9,
			"Minimum uptime (h)": 1,
			"Minimum downtime (h)": 1,
			"Initial status (h)": -24,
			"Initial power (MW)": 0.0
		},
		"g4": {
			"Bus": "b6",
			"Production cost curve (MW)": [0.8992148792351051, 22.275109867369967, 43.65100485550483, 65.02689984363968, 86.40279483177456],
			"Production cost curve ($)": [848.551414962958, 1594.5146442701787, 2520.030474640857, 3783.3547240156395, 5223.878506266689],
			"Startup costs ($)": [4274.52, 4497.57, 4827.67],
			"Startup delays (h)": [4.0, 8.0, 16.0],
			"Ramp up limit (MW)": 15.12,
			"Ramp down limit (MW)": 15.12,
			"Startup limit (MW)": 60.48,
			"Shutdown limit (MW)": 60.48,
			"Minimum uptime (h)": 4,
			"Minimum downtime (h)": 4,
			"Initial status (h)": -24,
			"Initial power (MW)": 0.0
		},
		"g5": {
			"Bus": "b8",
			"Production cost curve (MW)": [2.326914798402042, 23.12161589867012, 43.91631699893821, 64.71101809920629, 85.50571919947436],
			"Production cost curve ($)": [645.5555905711794, 1395.3861251379635, 2312.198895304892, 3543.1506774466516, 4879.427576009033],
			"Startup costs ($)": [5998.01, 6356.53, 6821.79],
			"Startup delays (h)": [1.0, 2.0, 4.0],
			"Ramp up limit (MW)": 14.9625,
			"Ramp down limit (MW)": 14.9625,
			"Startup limit (MW)": 59.85,
			"Shutdown limit (MW)": 59.85,
			"Minimum uptime (h)": 1,
			"Minimum downtime (h)": 1,
			"Initial status (h)": -24,
			"Initial power (MW)": 0.0
		}
	},
	"Transmission lines": {
		"l1": {
			"Source bus": "b1",
			"Target bus": "b2",
			"Reactance (ohms)": 0.05917000000000001,
			"Susceptance (S)": 29.496860773945063
		},
		"l2": {
			"Source bus": "b1",
			"Target bus": "b5",
			"Reactance (ohms)": 0.22304000000000002,
			"Susceptance (S)": 7.825184953346168
		},
		"l3": {
			"Source bus": "b2",
			"Target bus": "b3",
			"Reactance (ohms)": 0.19797,
			"Susceptance (S)": 8.816129979261149
		},
		"l4": {
			"Source bus": "b2",
			"Target bus": "b4",
			"Reactance (ohms)": 0.17632,
			"Susceptance (S)": 9.898645939169292
		},
		"l5": {
			"Source bus": "b2",
			"Target bus": "b5",
			"Reactance (ohms)": 0.17388,
			"Susceptance (S)": 10.037550333530765
		},
		"l6": {
			"Source bus": "b3",
			"Target bus": "b4",
			"Reactance (ohms)": 0.17103,
			"Susceptance (S)": 10.204813494675376
		},
		"l7": {
			"Source bus": "b4",
			"Target bus": "b5",
			"Reactance (ohms)": 0.04211,
			"Susceptance (S)": 41.44690695783257
		},
		"l8": {
			"Source bus": "b4",
			"Target bus": "b7",
			"Reactance (ohms)": 0.20911999999999997,
			"Susceptance (S)": 8.346065665619404
		},
		"l9": {
			"Source bus": "b4",
			"Target bus": "b9",
			"Reactance (ohms)": 0.55618,
			"Susceptance (S)": 3.1380654680037567
		},
		"l10": {
			"Source bus": "b5",
			"Target bus": "b6",
			"Reactance (ohms)": 0.25201999999999997,
			"Susceptance (S)": 6.92536009838239
		},
		"l11": {
			"Source bus": "b6",
			"Target bus": "b11",
			"Reactance (ohms)": 0.1989,
			"Susceptance (S)": 8.774908255376218
		},
		"l12": {
			"Source bus": "b6",
			"Target bus": "b12",
			"Reactance (ohms)": 0.25581,
			"Susceptance (S)": 6.8227561549365925
		},
		"l13": {
			"Source bus": "b6",
			"Target bus": "b13",
			"Reactance (ohms)": 0.13027,
			"Susceptance (S)": 13.397783465067395
		},
		"l14": {
			"Source bus": "b7",
			"Target bus": "b8",
			"Reactance (ohms)": 0.17615,
			"Susceptance (S)": 9.908198989465395
		},
		"l15": {
			"Source bus": "b7",
			"Target bus": "b9",
			"Reactance (ohms)": 0.11001,
			"Susceptance (S)": 15.865187273832648
		},
		"l16": {
			"Source bus": "b9",
			"Target bus": "b10",
			"Reactance (ohms)": 0.0845,
			"Susceptance (S)": 20.65478404727017
		},
		"l17": {
			"Source bus": "b9",
			"Target bus": "b14",
			"Reactance (ohms)": 0.27038,
			"Susceptance (S)": 6.4550974628091184
		},
		"l18": {
			"Source bus": "b10",
			"Target bus": "b11",
			"Reactance (ohms)": 0.19207,
			"Susceptance (S)": 9.08694357262628
		},
		"l19": {
			"Source bus": "b12",
			"Target bus": "b13",
			"Reactance (ohms)": 0.19988,
			"Susceptance (S)": 8.73188539120637
		},
		"l20": {
			"Source bus": "b13",
			"Target bus": "b14",
			"Reactance (ohms)": 0.34802,
			"Susceptance (S)": 5.0150257226433235
		}
	},
	"Buses": {
		"b1": {
			"s1": {
				"Load (MW)":[
					0.0,
					0.0,
					0.0,
					0.0,
					0.0,
					0.0,
					0.0,
					0.0,
					0.0,
					0.0,
					0.0,
					0.0,
					0.0,
					0.0,
					0.0,
					0.0,
					0.0,
					0.0,
					0.0,
					0.0,
					0.0,
					0.0,
					0.0,
					0.0,
					0.0,
					0.0,
					0.0,
					0.0,
					0.0,
					0.0,
					0.0,
					0.0,
					0.0,
					0.0,
					0.0,
					0.0,
					0.0,
					0.0,
					0.0,
					0.0,
					0.0,
					0.0,
					0.0,
					0.0,
					0.0,
					0.0,
					0.0,
					0.0
				],
"Probability":1
			}
		},
		"b2": {
			"s1": {
				"Load (MW)":[
					20.30650507453443,
					22.6762875744883,
					23.19657018691022,
					22.19807215085999,
					21.815413183963322,
					22.10968332936016,
					18.57598823890659,
					17.072212353417225,
					17.939097787396353,
					21.08731406152739,
					20.663837125582653,
					21.370451696098286,
					17.28049742932276,
					19.272036404858213,
					17.24038020023715,
					17.95817836931062,
					19.63385081896882,
					20.111581978212644,
					20.664242101126895,
					17.151126779679245,
					19.362085522410364,
					18.842328701131017,
					20.042302432360742,
					19.62069381811687,
					23.979280028631166,
					24.650381837948995,
					24.70013264985611,
					24.091611009189144,
					25.833674319550948,
					24.697391278785823,
					23.410162899657788,
					21.521492238201212,
					23.50953036903281,
					23.843786965102705,
					27.331575467392305,
					26.607435669654468,
					26.657210508739393,
					22.79839989982195,
					30.11984476460578,
					29.15227691927344,
					28.442800363399428,
					26.360031173599893,
					32.82431908144681,
					28.091023709638165,
					31.7148127796539,
					32.38992496983009,
					34.28537498771327,
					33.04185067033704
				],
"Probability":1
			}
		},
		"b3": {
			"s1": {
				"Load (MW)":[
					104.40708586144589,
					90.28411164834407,
					95.17664603895653,
					95.06209063932498,
					78.57419759786383,
					94.67964041055939,
					87.48506905443948,
					92.1663852133003,
					82.58102584492994,
					83.05165610402729,
					85.52239656146523,
					81.47525416083843,
					79.96869319935401,
					81.23915459256858,
					92.44116148126434,
					75.73157542879143,
					75.14119288922826,
					88.04722915986883,
					80.35211143186505,
					84.66578293468989,
					88.14641458991171,
					90.7239551686097,
					82.06034589185839,
					86.68470957093129,
					91.86065383475619,
					82.95728560534505,
					98.45552939842182,
					103.27254351665532,
					96.66431038489215,
					92.97057596210861,
					115.46790621425846,
					103.45076555142232,
					108.06969142535715,
					106.12203310419605,
					113.27684515832266,
					110.75631741943737,
					144.8663676057867,
					118.86239235722731,
					121.07726763966143,
					129.55877090704388,
					134.3986812026349,
					151.64042284751338,
					125.43323038653988,
					118.47159773316578,
					131.64367785574933,
					146.5500085406521,
					145.2189091785475,
					122.06467164953526
				],
"Probability":1
			}
		},
		"b4": {
			"s1": {
				"Load (MW)":[
					45.73167455936368,
					43.46973960531654,
					50.1283659090007,
					47.08121704680666,
					45.02828463797493,
					48.6681291207772,
					49.4978060881202,
					43.19674045962024,
					44.29235238413219,
					45.2009122476229,
					43.2170938656548,
					50.00670917583291,
					38.86261939786642,
					42.070197205129126,
					43.253206799911084,
					37.96707007092436,
					41.83825186651733,
					38.89204521970121,
					39.36968899115888,
					48.48820058701697,
					43.916046209737885,
					46.15364114233648,
					43.13529511257748,
					47.151232910318384,
					55.028117294021826,
					52.867646340271506,
					42.40194434667356,
					43.75845827416357,
					52.015934053696775,
					57.329463403439696,
					50.29289525886565,
					58.855581222828924,
					51.404976142963115,
					60.00920867380702,
					61.337655100464424,
					51.10795455730949,
					61.01124989036034,
					65.04087733246728,
					64.1218260818639,
					55.19025794898405,
					62.855257631627154,
					58.586362509400054,
					67.63241124882411,
					73.80304829010733,
					70.3149125765222,
					71.29380149685537,
					68.95058483903078,
					68.15250949849008
				],
"Probability":1
			}
		},
		"b5": {
			"s1": {
				"Load (MW)":[
					8.49376965868678,
					6.688501425891067,
					6.904792709948409,
					7.838637149280954,
					7.224378440343838,
					7.264352645931047,
					6.316563083538417,
					8.343843369901574,
					6.823362226493596,
					6.488942040973683,
					7.255403385713041,
					6.090794396709614,
					5.9861103650431,
					7.167303247750244,
					6.092629656171984,
					5.666423235662061,
					5.587980273335903,
					6.6618566425318315,
					6.108360552833209,
					6.103830939400608,
					7.152904842990879,
					7.342190708155906,
					8.00670203701033,
					5.805484929105684,
					7.793456972077285,
					7.986056574337922,
					8.101451782926382,
					7.625534674598446,
					8.667262800156307,
					8.058747258762565,
					8.362198868124995,
					8.180939498631426,
					8.614587998250666,
					7.48558232851348,
					8.72567375863936,
					8.548857603608726,
					10.215494600995486,
					10.295305339080807,
					9.865999882281947,
					9.72072285831143,
					10.746716359790536,
					11.433182070803635,
					10.470697156692212,
					10.224265522575548,
					8.21138533756884,
					12.427788857890592,
					12.166065729506585,
					10.137754306625173
				],
"Probability":1
			}
		},
		"b6": {
			"s1": {
				"Load (MW)":[
					11.320612815898409,
					10.977634262398807,
					12.677104070451778,
					10.566951938623687,
					10.549154745868274,
					12.143522534458356,
					11.186713493624103,
					9.485065792142267,
					10.261190840600964,
					9.848502662736777,
					11.094296811111796,
					10.359718410832997,
					8.634567656475557,
					9.907892335298756,
					9.617176037688326,
					10.19459895764851,
					10.304453109894707,
					10.128535803891996,
					10.140470143719655,
					9.225733981933281,
					9.610915406972502,
					10.240792906082016,
					10.600101616316305,
					11.142284034897491,
					11.690073489796076,
					10.801184928211006,
					11.101229368736822,
					10.845259839093702,
					11.835060948812298,
					12.311046987426646,
					12.765504120247272,
					12.446554824768155,
					14.09249153963012,
					13.859466485400686,
					14.28004455252514,
					12.984248404914192,
					14.355582026033344,
					15.284809378222084,
					15.021986177110183,
					15.555696524428038,
					14.817273714840377,
					16.074679961179896,
					15.570527678545163,
					17.864799479781173,
					17.68376198511312,
					13.636538231325392,
					15.657834613907648,
					14.539711254379187
				],
"Probability":1
			}
		},
		"b7": {
			"s1": {
				"Load (MW)":[
					0.0,
					0.0,
					0.0,
					0.0,
					0.0,
					0.0,
					0.0,
					0.0,
					0.0,
					0.0,
					0.0,
					0.0,
					0.0,
					0.0,
					0.0,
					0.0,
					0.0,
					0.0,
					0.0,
					0.0,
					0.0,
					0.0,
					0.0,
					0.0,
					0.0,
					0.0,
					0.0,
					0.0,
					0.0,
					0.0,
					0.0,
					0.0,
					0.0,
					0.0,
					0.0,
					0.0,
					0.0,
					0.0,
					0.0,
					0.0,
					0.0,
					0.0,
					0.0,
					0.0,
					0.0,
					0.0,
					0.0,
					0.0
				],
"Probability":1
			}
		},
		"b8": {
			"s1": {
				"Load (MW)":[
					0.0,
					0.0,
					0.0,
					0.0,
					0.0,
					0.0,
					0.0,
					0.0,
					0.0,
					0.0,
					0.0,
					0.0,
					0.0,
					0.0,
					0.0,
					0.0,
					0.0,
					0.0,
					0.0,
					0.0,
					0.0,
					0.0,
					0.0,
					0.0,
					0.0,
					0.0,
					0.0,
					0.0,
					0.0,
					0.0,
					0.0,
					0.0,
					0.0,
					0.0,
					0.0,
					0.0,
					0.0,
					0.0,
					0.0,
					0.0,
					0.0,
					0.0,
					0.0,
					0.0,
					0.0,
					0.0,
					0.0,
					0.0
				],
"Probability":1
			}
		},
		"b9": {
			"s1": {
				"Load (MW)":[
					30.64090500883641,
					27.219882832043968,
					30.11284128159429,
					28.62677855925169,
					24.721464068656122,
					25.567479734996134,
					29.863621261280258,
					24.97807519290469,
					24.49631970518596,
					30.335918422923235,
					26.215838138488106,
					25.966439754112113,
					28.55939298247011,
					27.803909563853278,
					27.31361978988809,
					28.282094317128944,
					26.084679590494208,
					27.20241373174025,
					25.282030982991987,
					27.521866247231912,
					30.46805244424695,
					27.609179803908674,
					23.9944447255023,
					31.56027182436,
					27.77390131037322,
					32.633093421956914,
					30.577739401666353,
					28.477163060313845,
					31.504362724077932,
					31.432025063638914,
					31.205558627759775,
					29.436384141234964,
					34.70074135015003,
					33.551649254926474,
					36.85868565971388,
					33.08060359393513,
					39.57792065117699,
					37.978153789176176,
					37.148723492824004,
					39.223030976088566,
					40.500496173245786,
					46.49347344173272,
					40.23175271631681,
					36.260406646267555,
					43.631289261621845,
					42.43561299019263,
					44.20494496071717,
					47.06079236526112
				],
"Probability":1
			}
		},
		"b10": {
			"s1": {
				"Load (MW)":[
					8.956576696346886,
					9.943646302567354,
					9.983180332612147,
					9.291828565030244,
					9.35607017326705,
					8.460424453037808,
					8.877817259447868,
					7.838888748645636,
					8.683996718081154,
					9.022856492095242,
					7.493751090490023,
					7.61069130061776,
					7.31196657986043,
					8.510090804441298,
					7.626816840973275,
					7.647887800303032,
					8.829703847703334,
					9.04156071322602,
					8.204524871602338,
					7.430584068573042,
					8.390840767092836,
					8.915259078123407,
					9.352971263635784,
					9.413965337072986,
					7.64092345744533,
					8.672167125658724,
					9.39505120522639,
					7.626944643019098,
					8.603482958882976,
					9.816611082771153,
					9.86447820619696,
					10.318105536708334,
					10.68836887964162,
					10.580772161359873,
					11.113860183932582,
					10.311447699190724,
					10.626696651019879,
					13.548503176313814,
					12.688880767612888,
					10.983921285476583,
					11.528433206157871,
					14.415081251160048,
					13.024492331820126,
					12.457262747779446,
					12.362326015594755,
					12.267394399715098,
					13.381029425894374,
					11.955118847923375
				],
"Probability":1
			}
		},
		"b11": {
			"s1": {
				"Load (MW)":[
					3.2027334268230074,
					3.3442742262283542,
					3.7134989356062476,
					3.0518304008251955,
					3.385025107792687,
					2.933874801604748,
					2.9427302332519814,
					3.253388881596727,
					3.1539709543907612,
					2.8420417117866945,
					3.0139030701488454,
					3.0250458239796916,
					2.60113673201151,
					3.259550218860122,
					3.112442429869031,
					3.2815469470674508,
					3.1936686963161374,
					3.5842470976266334,
					2.7522964240069347,
					2.6234257366057427,
					2.8927276025303628,
					3.2163427148211166,
					3.0649606812582855,
					3.4163356620990375,
					3.8860595486850977,
					3.7064841408840277,
					3.6204881571768195,
					3.5494836594946073,
					3.742608990562221,
					4.204747873084872,
					3.3569274428860645,
					4.054290037700302,
					3.5838311132877703,
					4.529304507033256,
					4.417209724587741,
					4.673227432296622,
					4.443886810277442,
					4.74036307443555,
					3.880790979135136,
					4.54721094797442,
					4.6234787546921705,
					5.194457345467711,
					4.5568305428169555,
					4.356213134407474,
					5.32291287950559,
					4.743521934537183,
					5.0632194065540945,
					5.315836070028426
				],
"Probability":1
			}
		},
		"b12": {
			"s1": {
				"Load (MW)":[
					6.5569759985403895,
					5.140768272934949,
					5.832637096302932,
					7.08760998012701,
					5.879053170914474,
					6.296500398778728,
					6.109863040979375,
					5.4292184004087485,
					6.073206117847445,
					5.238758825143739,
					5.1044036958898955,
					5.151427988337368,
					5.655104300716634,
					5.127213649435425,
					5.607213513426468,
					4.837750052316877,
					5.414203834599268,
					4.604569376985685,
					5.476286409577521,
					5.249748912739884,
					6.736910002529847,
					5.5491996463127276,
					5.809288019033057,
					5.719502464879837,
					5.367976954867461,
					6.17953656792027,
					5.645282220174235,
					5.944740430631914,
					6.874572928602051,
					6.982884314294468,
					7.21956480183517,
					7.148824991066238,
					7.090677602506553,
					7.889807773138614,
					7.629915014907332,
					7.576356067419075,
					7.566594223963611,
					8.303329384181422,
					7.959690546259328,
					7.516087578112257,
					8.821329559291584,
					8.05608945922567,
					8.381353172787051,
					8.01396307794916,
					7.9563436337598015,
					9.224724115039566,
					7.905630505472181,
					8.77477650633251
				],
"Probability":1
			}
		},
		"b13": {
			"s1": {
				"Load (MW)":[
					11.86984619098784,
					13.895104613919564,
					14.882629026473353,
					12.130543619050552,
					11.923978868708563,
					12.09612807677257,
					10.375648801615734,
					13.516499500781833,
					10.281361189093497,
					11.777938187085258,
					11.321643643689281,
					11.835987605321296,
					10.76780055015027,
					12.062997915604653,
					11.983074423570464,
					11.916979135733401,
					10.519486108278475,
					12.298575468867593,
					14.144255883789942,
					12.290323212205637,
					11.609019934368657,
					12.700127908310105,
					12.73266858122068,
					12.94969450072823,
					12.876749059700014,
					12.889617964374457,
					11.737164474570426,
					13.582538482631714,
					15.66120254410038,
					14.48274288489735,
					13.580840800466648,
					16.00248184492051,
					17.105365978583023,
					17.60471521807348,
					14.995400030171254,
					16.063751117435203,
					16.85354119504811,
					19.30435422077112,
					15.952786033092321,
					17.3295568773396,
					16.825198922367214,
					17.950405262261643,
					17.61540810175109,
					17.81513924261194,
					19.757920611677672,
					18.2202618420771,
					20.705191658883997,
					18.2887656582555
				],
"Probability":1
			}
		},
		"b14": {
			"s1": {
				"Load (MW)":[
					13.748871532384706,
					14.779393681627758,
					17.19593922378249,
					14.36029245038678,
					15.214860701463822,
					14.66176409327748,
					13.581614950682873,
					14.030710392330896,
					11.852491974825307,
					12.241849688947822,
					13.137744293240702,
					13.874088981327073,
					11.783671832116646,
					13.336693067789398,
					14.002777132250417,
					12.535780711526842,
					13.018674441406107,
					11.854653121631292,
					12.050489597745168,
					13.065967066019528,
					15.239704558004073,
					13.680779848902088,
					13.780639437705888,
					14.532826201523807,
					18.089189242816396,
					15.50168128833228,
					14.504838160157597,
					13.844394346551285,
					16.113669152100975,
					17.02962299561733,
					15.855782564091644,
					14.650376046437902,
					18.745210876670495,
					18.13773593724745,
					18.863968370752975,
					17.34679945672238,
					19.088015521341262,
					16.589325583122708,
					18.041727540588138,
					19.049407638714964,
					18.991252507561146,
					22.223150914079003,
					16.87613452085509,
					21.792547268533152,
					22.283082084616158,
					21.575451475507773,
					20.575413571864726,
					20.258213548126587
				],
"Probability":1
			}
		}
	}
}