{
"Parameters": {
	"Power balance penalty ($/MW)": [10000.0, 10000.0, 10000.0, 10000.0, 10000.0, 10000.0, 10000.0, 10000.0, 10000.0, 10000.0, 10000.0, 10000.0, 10000.0, 10000.0, 10000.0, 10000.0, 10000.0, 10000.0, 10000.0, 10000.0, 10000.0, 10000.0, 10000.0, 10000.0, 10000.0, 10000.0, 10000.0, 10000.0, 10000.0, 10000.0, 10000.0, 10000.0, 10000.0, 10000.0, 10000.0, 10000.0, 10000.0, 10000.0, 10000.0, 10000.0, 10000.0, 10000.0, 10000.0, 10000.0, 10000.0, 10000.0, 10000.0, 10000.0, 10000.0, 10000.0, 10000.0, 10000.0, 10000.0, 10000.0, 10000.0, 10000.0, 10000.0, 10000.0, 10000.0, 10000.0, 10000.0, 10000.0, 10000.0, 10000.0, 10000.0, 10000.0, 10000.0, 10000.0, 10000.0, 10000.0, 10000.0, 10000.0, 10000.0, 10000.0, 10000.0, 10000.0, 10000.0, 10000.0, 10000.0, 10000.0, 10000.0, 10000.0, 10000.0, 10000.0, 10000.0, 10000.0, 10000.0, 10000.0, 10000.0, 10000.0, 10000.0, 10000.0, 10000.0, 10000.0, 10000.0, 10000.0],
	"Scenario number": 1,
	"Time horizon (h)": 15,
	"Time step (min)": 15},
	"Generators": {
		"g1": {
			"Bus": "b1",
			"Production cost curve (MW)": [16.901100444445653, 94.40345818607902, 171.90581592771244, 249.40817366934598, 326.91053141097933],
			"Production cost curve ($)": [716.7470233305867, 3465.763907745978, 6335.568940853531, 9252.345705326847, 12232.933634581022],
			"Startup costs ($)": [20559.35, 24224.12, 28727.63],
			"Startup delays (h)": [1.0, 2.0, 4.0],
			"Ramp up limit (MW)": 57.21,
			"Ramp down limit (MW)": 57.21,
			"Startup limit (MW)": 228.84,
			"Shutdown limit (MW)": 228.84,
			"Minimum uptime (h)": 1,
			"Minimum downtime (h)": 1,
			"Initial status (h)": 24,
			"Initial power (MW)": 257.74170000000004
		},
		"g2": {
			"Bus": "b2",
			"Production cost curve (MW)": [2.257203830814138, 33.5985679204243, 64.93993201003447, 96.28129609964463, 127.62266018925479],
			"Production cost curve ($)": [953.4271497797719, 2139.086577758979, 3416.0435375709003, 4856.980529832745, 6523.928912640124],
			"Startup costs ($)": [10345.29, 10498.58, 10598.13],
			"Startup delays (h)": [1.0, 2.0, 4.0],
			"Ramp up limit (MW)": 22.335,
			"Ramp down limit (MW)": 22.335,
			"Startup limit (MW)": 89.34,
			"Shutdown limit (MW)": 89.34,
			"Minimum uptime (h)": 1,
			"Minimum downtime (h)": 1,
			"Initial status (h)": -24,
			"Initial power (MW)": 0.0
		},
		"g3": {
			"Bus": "b3",
			"Production cost curve (MW)": [1.619043590917833, 21.894126410542157, 42.16920923016648, 62.444292049790796, 82.71937486941513],
			"Production cost curve ($)": [685.7745024725275, 1403.8176490424148, 2365.8595550594155, 3786.959826482599, 5342.322597393779],
			"Startup costs ($)": [4382.12, 4505.39, 4595.43],
			"Startup delays (h)": [1.0, 2.0, 4.0],
			"Ramp up limit (MW)": 14.475,
			"Ramp down limit (MW)": 14.475,
			"Startup limit (MW)": 57.9,
			"Shutdown limit (MW)": 57.9,
			"Minimum uptime (h)": 1,
			"Minimum downtime (h)": 1,
			"Initial status (h)": -24,
			"Initial power (MW)": 0.0
		},
		"g4": {
			"Bus": "b6",
			"Production cost curve (MW)": [0.8992148792351051, 22.275109867369967, 43.65100485550483, 65.02689984363968, 86.40279483177456],
			"Production cost curve ($)": [848.551414962958, 1594.5146442701787, 2520.030474640857, 3783.3547240156395, 5223.878506266689],
			"Startup costs ($)": [4274.52, 4497.57, 4827.67],
			"Startup delays (h)": [4.0, 8.0, 16.0],
			"Ramp up limit (MW)": 15.12,
			"Ramp down limit (MW)": 15.12,
			"Startup limit (MW)": 60.48,
			"Shutdown limit (MW)": 60.48,
			"Minimum uptime (h)": 4,
			"Minimum downtime (h)": 4,
			"Initial status (h)": -24,
			"Initial power (MW)": 0.0
		},
		"g5": {
			"Bus": "b8",
			"Production cost curve (MW)": [2.326914798402042, 23.12161589867012, 43.91631699893821, 64.71101809920629, 85.50571919947436],
			"Production cost curve ($)": [645.5555905711794, 1395.3861251379635, 2312.198895304892, 3543.1506774466516, 4879.427576009033],
			"Startup costs ($)": [5998.01, 6356.53, 6821.79],
			"Startup delays (h)": [1.0, 2.0, 4.0],
			"Ramp up limit (MW)": 14.9625,
			"Ramp down limit (MW)": 14.9625,
			"Startup limit (MW)": 59.85,
			"Shutdown limit (MW)": 59.85,
			"Minimum uptime (h)": 1,
			"Minimum downtime (h)": 1,
			"Initial status (h)": -24,
			"Initial power (MW)": 0.0
		}
	},
	"Transmission lines": {
		"l1": {
			"Source bus": "b1",
			"Target bus": "b2",
			"Reactance (ohms)": 0.05917000000000001,
			"Susceptance (S)": 29.496860773945063
		},
		"l2": {
			"Source bus": "b1",
			"Target bus": "b5",
			"Reactance (ohms)": 0.22304000000000002,
			"Susceptance (S)": 7.825184953346168
		},
		"l3": {
			"Source bus": "b2",
			"Target bus": "b3",
			"Reactance (ohms)": 0.19797,
			"Susceptance (S)": 8.816129979261149
		},
		"l4": {
			"Source bus": "b2",
			"Target bus": "b4",
			"Reactance (ohms)": 0.17632,
			"Susceptance (S)": 9.898645939169292
		},
		"l5": {
			"Source bus": "b2",
			"Target bus": "b5",
			"Reactance (ohms)": 0.17388,
			"Susceptance (S)": 10.037550333530765
		},
		"l6": {
			"Source bus": "b3",
			"Target bus": "b4",
			"Reactance (ohms)": 0.17103,
			"Susceptance (S)": 10.204813494675376
		},
		"l7": {
			"Source bus": "b4",
			"Target bus": "b5",
			"Reactance (ohms)": 0.04211,
			"Susceptance (S)": 41.44690695783257
		},
		"l8": {
			"Source bus": "b4",
			"Target bus": "b7",
			"Reactance (ohms)": 0.20911999999999997,
			"Susceptance (S)": 8.346065665619404
		},
		"l9": {
			"Source bus": "b4",
			"Target bus": "b9",
			"Reactance (ohms)": 0.55618,
			"Susceptance (S)": 3.1380654680037567
		},
		"l10": {
			"Source bus": "b5",
			"Target bus": "b6",
			"Reactance (ohms)": 0.25201999999999997,
			"Susceptance (S)": 6.92536009838239
		},
		"l11": {
			"Source bus": "b6",
			"Target bus": "b11",
			"Reactance (ohms)": 0.1989,
			"Susceptance (S)": 8.774908255376218
		},
		"l12": {
			"Source bus": "b6",
			"Target bus": "b12",
			"Reactance (ohms)": 0.25581,
			"Susceptance (S)": 6.8227561549365925
		},
		"l13": {
			"Source bus": "b6",
			"Target bus": "b13",
			"Reactance (ohms)": 0.13027,
			"Susceptance (S)": 13.397783465067395
		},
		"l14": {
			"Source bus": "b7",
			"Target bus": "b8",
			"Reactance (ohms)": 0.17615,
			"Susceptance (S)": 9.908198989465395
		},
		"l15": {
			"Source bus": "b7",
			"Target bus": "b9",
			"Reactance (ohms)": 0.11001,
			"Susceptance (S)": 15.865187273832648
		},
		"l16": {
			"Source bus": "b9",
			"Target bus": "b10",
			"Reactance (ohms)": 0.0845,
			"Susceptance (S)": 20.65478404727017
		},
		"l17": {
			"Source bus": "b9",
			"Target bus": "b14",
			"Reactance (ohms)": 0.27038,
			"Susceptance (S)": 6.4550974628091184
		},
		"l18": {
			"Source bus": "b10",
			"Target bus": "b11",
			"Reactance (ohms)": 0.19207,
			"Susceptance (S)": 9.08694357262628
		},
		"l19": {
			"Source bus": "b12",
			"Target bus": "b13",
			"Reactance (ohms)": 0.19988,
			"Susceptance (S)": 8.73188539120637
		},
		"l20": {
			"Source bus": "b13",
			"Target bus": "b14",
			"Reactance (ohms)": 0.34802,
			"Susceptance (S)": 5.0150257226433235
		}
	},
	"Buses": {
		"b1": {
			"s1": {
				"Load (MW)":[
					0.0,
					0.0,
					0.0,
					0.0,
					0.0,
					0.0,
					0.0,
					0.0,
					0.0,
					0.0,
					0.0,
					0.0,
					0.0,
					0.0,
					0.0,
					0.0,
					0.0,
					0.0,
					0.0,
					0.0,
					0.0,
					0.0,
					0.0,
					0.0,
					0.0,
					0.0,
					0.0,
					0.0,
					0.0,
					0.0,
					0.0,
					0.0,
					0.0,
					0.0,
					0.0,
					0.0,
					0.0,
					0.0,
					0.0,
					0.0,
					0.0,
					0.0,
					0.0,
					0.0,
					0.0,
					0.0,
					0.0,
					0.0,
					0.0,
					0.0,
					0.0,
					0.0,
					0.0,
					0.0,
					0.0,
					0.0,
					0.0,
					0.0,
					0.0,
					0.0
				],
"Probability":1
			}
		},
		"b2": {
			"s1": {
				"Load (MW)":[
					22.229414259207932,
					23.730866668624387,
					21.45889655947204,
					25.025546627127163,
					20.159815459393993,
					21.377591005794642,
					21.711964118089007,
					22.354088073749153,
					18.157530316008714,
					17.76992676032751,
					22.80996365732039,
					16.59941702375331,
					21.700356800529747,
					18.702323877135576,
					21.551598714454286,
					18.39898366732846,
					20.995930902766105,
					19.5509475213073,
					18.591072716199058,
					16.966150126473334,
					17.966841896232722,
					17.581793104064467,
					18.90678649980579,
					16.838105980056422,
					20.798516149656532,
					23.24131510282238,
					25.699147393315332,
					23.479815650932352,
					23.586130743156374,
					20.09419110259963,
					22.92815482862263,
					25.883826310320174,
					25.158442013954392,
					27.773642283099427,
					28.04019693547111,
					29.392000739214208,
					28.46140571338558,
					22.721411429942556,
					27.45824132303442,
					24.709646384090696,
					27.014651864244062,
					30.96560087027547,
					31.098390355538022,
					30.35776875673063,
					29.21595767009283,
					29.80432415386095,
					29.413512556470838,
					30.760350957607503,
					31.487760138795746,
					31.046859014264335,
					31.910538080761583,
					31.354284531642644,
					27.670048181753213,
					33.378884769842024,
					36.14232665306136,
					33.92563135235065,
					34.998850759899724,
					37.187764957762866,
					37.945012775266385,
					30.35194183027349
				],
"Probability":1
			}
		},
		"b3": {
			"s1": {
				"Load (MW)":[
					106.47190335026953,
					97.08104937661022,
					83.69915897654764,
					91.93585545806154,
					96.0885622594873,
					98.47763963365958,
					90.60792053629056,
					85.5139889370294,
					82.51122898636727,
					82.83929490582204,
					85.39670177017682,
					84.15349596727943,
					84.66071265909272,
					78.99894095688329,
					90.23686999318222,
					76.52866772314425,
					77.92394906462224,
					84.3015465014641,
					65.26000681823814,
					77.8496357992669,
					82.95179521797444,
					100.81107190395491,
					81.45209580082397,
					80.29436180720609,
					97.49632435401224,
					109.07883648008716,
					97.66164728615085,
					100.9600379381169,
					99.08909428914674,
					107.9091898458419,
					103.61765646544441,
					95.15781118113468,
					115.07915713809976,
					103.3848590042277,
					113.62478773973956,
					97.90268131382228,
					116.42924812166495,
					139.4832347932461,
					132.28112952151287,
					126.95431788350095,
					116.58224059646375,
					141.1338753775315,
					142.1743305203424,
					127.76274900040329,
					131.35032283955513,
					125.44639140855966,
					125.83811774291185,
					127.27028850063994,
					144.68668137300395,
					140.7910480533726,
					138.82116086215683,
					162.32042400168325,
					128.70514762222678,
					132.15308135303167,
					142.45449294790475,
					164.0544470681282,
					127.82665423866749,
					148.5473288881858,
					154.7467187067688,
					159.54811293521408
				],
"Probability":1
			}
		},
		"b4": {
			"s1": {
				"Load (MW)":[
					45.11527283830682,
					47.23147349628959,
					50.627301700205024,
					48.51390942931069,
					46.80359418284485,
					45.94971120586208,
					49.36402531480293,
					41.182334798093535,
					38.16905412487458,
					39.769739997993625,
					39.18392952734922,
					45.83779576336564,
					45.51796011680421,
					39.47670135790933,
					41.585455024580455,
					42.72624999356788,
					40.76888530115461,
					41.041677808391576,
					45.73030278030151,
					43.89777141714139,
					44.931534872682775,
					45.434002404110345,
					38.79607279826567,
					45.858737172685004,
					50.65058580468436,
					50.76945830529193,
					44.6730740322839,
					53.21974998342483,
					57.98464309487326,
					56.824464759558,
					53.586551008403305,
					48.223121072864835,
					56.46275570478505,
					56.82054352343749,
					54.53515794579219,
					54.45248543434687,
					62.0854522083927,
					63.81704993961321,
					67.65880186596985,
					61.86181186704034,
					56.824762492383066,
					63.41292149118863,
					71.24124603414171,
					74.242805612189,
					68.06549635901597,
					69.44425654220679,
					72.93652140892405,
					69.95030703322844,
					65.15212972040669,
					64.03296671511295,
					78.88074110836098,
					66.05492539220316,
					68.73407193716577,
					78.48940137872721,
					74.04794126517648,
					54.76749212854629,
					72.61358838296316,
					82.53384485248853,
					72.38497765052523,
					71.92394076327128
				],
"Probability":1
			}
		},
		"b5": {
			"s1": {
				"Load (MW)":[
					7.0479192194830995,
					7.2867702435900314,
					8.704559090794273,
					6.905813579870367,
					7.8887567230453906,
					7.65751299644582,
					7.040093316843912,
					7.615197209889847,
					6.888005373312567,
					7.378293894671265,
					7.704326685748677,
					7.322686481296414,
					6.307598743055028,
					6.515757379000864,
					7.216095002719669,
					6.628698962801478,
					6.57529447597147,
					6.094637363672591,
					6.524923237773342,
					6.345173650308944,
					6.974992037980172,
					6.67091045724329,
					6.810216433974425,
					6.387036935827126,
					8.452486337407612,
					6.796486593534796,
					7.354036110932643,
					8.19673284528612,
					7.896525494120425,
					8.08543583440354,
					7.811207971371223,
					10.125012800494183,
					8.52678144448116,
					9.783941747641483,
					8.626291264847735,
					8.988243802641911,
					9.684345183838682,
					10.031368621300825,
					10.387535944451265,
					9.501489710512091,
					9.856216109325366,
					9.244099034769276,
					9.421815429985706,
					9.644119322715786,
					11.433033592063177,
					10.203033741619697,
					10.771380649307119,
					11.174183109677118,
					9.881412954434417,
					9.623064229196903,
					12.153492620269528,
					10.690082939534959,
					10.630041332721309,
					10.758706258611852,
					12.783992444318175,
					11.536428586076966,
					11.456669195868203,
					11.053504181697878,
					13.39595286574915,
					11.05310750348892
				],
"Probability":1
			}
		},
		"b6": {
			"s1": {
				"Load (MW)":[
					10.031874978668696,
					11.629673677568183,
					11.516234126537444,
					12.627675569428067,
					11.003273194008523,
					7.940022852114984,
					10.231028422032871,
					10.471950745262452,
					12.141547189846193,
					10.396860400432239,
					11.406982530159137,
					9.979946135821875,
					10.396855436919383,
					10.03875160451535,
					9.610779152709842,
					10.112622429331735,
					9.221486801125941,
					11.104386025004846,
					11.414509235294926,
					10.300177767063964,
					10.14547444463015,
					8.496114105160594,
					11.138498593500636,
					10.64715712363057,
					12.199375282887589,
					10.434842455808935,
					11.509820762583498,
					11.127563299448044,
					13.294116933144819,
					12.470295061172006,
					13.133132158249879,
					11.6789253533536,
					12.552114026886409,
					12.157642942782477,
					13.230005561926461,
					11.933166145834479,
					13.87154052392962,
					14.911104034196443,
					13.82530062627847,
					14.357945472386335,
					16.831842340858472,
					16.364070274106677,
					14.869187831885764,
					14.826854787300267,
					15.48619487313403,
					14.057774199995498,
					16.500420649966586,
					17.72968123193036,
					15.73635735807009,
					15.771505745480624,
					17.423484611230407,
					16.168627250452033,
					15.477293347868974,
					16.904899771604736,
					18.575316831577062,
					17.14793900368101,
					16.363529030349955,
					18.899284710464986,
					17.524816627526402,
					17.421008837312485
				],
"Probability":1
			}
		},
		"b7": {
			"s1": {
				"Load (MW)":[
					0.0,
					0.0,
					0.0,
					0.0,
					0.0,
					0.0,
					0.0,
					0.0,
					0.0,
					0.0,
					0.0,
					0.0,
					0.0,
					0.0,
					0.0,
					0.0,
					0.0,
					0.0,
					0.0,
					0.0,
					0.0,
					0.0,
					0.0,
					0.0,
					0.0,
					0.0,
					0.0,
					0.0,
					0.0,
					0.0,
					0.0,
					0.0,
					0.0,
					0.0,
					0.0,
					0.0,
					0.0,
					0.0,
					0.0,
					0.0,
					0.0,
					0.0,
					0.0,
					0.0,
					0.0,
					0.0,
					0.0,
					0.0,
					0.0,
					0.0,
					0.0,
					0.0,
					0.0,
					0.0,
					0.0,
					0.0,
					0.0,
					0.0,
					0.0,
					0.0
				],
"Probability":1
			}
		},
		"b8": {
			"s1": {
				"Load (MW)":[
					0.0,
					0.0,
					0.0,
					0.0,
					0.0,
					0.0,
					0.0,
					0.0,
					0.0,
					0.0,
					0.0,
					0.0,
					0.0,
					0.0,
					0.0,
					0.0,
					0.0,
					0.0,
					0.0,
					0.0,
					0.0,
					0.0,
					0.0,
					0.0,
					0.0,
					0.0,
					0.0,
					0.0,
					0.0,
					0.0,
					0.0,
					0.0,
					0.0,
					0.0,
					0.0,
					0.0,
					0.0,
					0.0,
					0.0,
					0.0,
					0.0,
					0.0,
					0.0,
					0.0,
					0.0,
					0.0,
					0.0,
					0.0,
					0.0,
					0.0,
					0.0,
					0.0,
					0.0,
					0.0,
					0.0,
					0.0,
					0.0,
					0.0,
					0.0,
					0.0
				],
"Probability":1
			}
		},
		"b9": {
			"s1": {
				"Load (MW)":[
					25.453904309834634,
					32.94119417378812,
					27.57787382475231,
					29.409485585693673,
					23.941319016243135,
					24.74005014668502,
					32.00427742852338,
					25.966439180753113,
					23.71626548886518,
					22.48539136949897,
					25.483344394769997,
					27.62031300110929,
					27.529830372857887,
					28.34371147376555,
					26.024434851041356,
					27.355374618232492,
					24.072769882083744,
					27.128003796816266,
					26.248376190654145,
					25.618802307931414,
					30.6952462412701,
					25.76303648899016,
					29.89666600563635,
					28.065393992851607,
					30.49223694390606,
					30.39581332562914,
					27.4280370494979,
					29.593310518792507,
					31.559121337749552,
					30.903756486441278,
					32.658048505248175,
					31.558763111704998,
					39.155285274208175,
					33.358750761659735,
					31.422081137001758,
					33.40148805473661,
					39.92582479214786,
					38.24575053390931,
					43.79127709336457,
					38.64357340087227,
					48.12328374533908,
					39.034835823651086,
					34.26313035614386,
					44.93313697271859,
					45.687846957377566,
					44.54269021161922,
					33.38857916675183,
					37.963147158260384,
					43.93261830189239,
					42.794224755666605,
					47.047464947940085,
					45.802103583043966,
					46.1345621020079,
					48.06136879829728,
					46.659373346515665,
					42.61971116232597,
					50.142409256824706,
					43.94344638479773,
					48.00395012326125,
					44.8248398027204
				],
"Probability":1
			}
		},
		"b10": {
			"s1": {
				"Load (MW)":[
					9.41421093050068,
					9.118774574369887,
					9.424396413937542,
					8.570877840208693,
					9.504893207325255,
					8.960454536075863,
					7.786238193586457,
					7.9692457944557615,
					7.99773747942764,
					7.628527786484364,
					8.474641947030495,
					8.064268691799876,
					7.890380024573982,
					8.814078877506134,
					7.561918461070588,
					7.449370155256785,
					7.914837916170634,
					8.189249377584257,
					8.277723357182891,
					8.520280837690775,
					7.8786463133568105,
					9.44207621510504,
					9.256583640297798,
					8.126203174165378,
					9.381503976977577,
					7.594296089795316,
					9.305099701633367,
					10.054975597985951,
					9.930235765339443,
					9.794075299366959,
					11.443885230489405,
					8.973491928075997,
					9.134649496552562,
					9.27893933704221,
					11.275386508392314,
					10.916437029154244,
					12.360827282428717,
					10.916650713052636,
					11.210978802414116,
					11.710018327969946,
					12.547617252162787,
					12.652114515713947,
					12.14652128050884,
					11.72760033627998,
					11.333740267101254,
					11.634626087685936,
					12.16617040784849,
					13.169026657228644,
					13.282481135393873,
					14.444962097600099,
					12.770576583834151,
					12.341168903742638,
					13.074428381456588,
					13.211776015812404,
					12.390245413723841,
					14.417399349848873,
					13.968409463905777,
					14.773118062592948,
					14.303813936855818,
					14.58228471742038
				],
"Probability":1
			}
		},
		"b11": {
			"s1": {
				"Load (MW)":[
					4.021117572036853,
					3.5059739545393143,
					3.0101354401667098,
					2.9440375031338055,
					3.4037239777436437,
					2.8918551133216512,
					3.3528042115110503,
					3.7101438635831023,
					2.9741658856648363,
					3.033812796774678,
					2.796470883843432,
					2.9529638510710794,
					3.0014460370533333,
					3.261574317300975,
					3.4804425882460985,
					3.2441426170764087,
					3.052245199013065,
					2.8873637853016483,
					3.0526928659268697,
					3.3026585002868285,
					3.6244627116275563,
					3.530644158228287,
					3.018921546546186,
					3.342178398860623,
					3.8815346066222056,
					2.901030855758706,
					3.843070802346131,
					3.7710985685844336,
					3.81541681103947,
					3.857846679617753,
					4.236146506256267,
					3.7740654163194542,
					4.435873888334632,
					4.424268315469437,
					3.8985057755943004,
					3.952361844326704,
					4.403356318771503,
					4.110287171299585,
					5.061684667886062,
					4.7533382564213325,
					4.180072799046049,
					5.165657448011983,
					5.507100445970165,
					5.179685487926147,
					5.322529316514723,
					4.137453542789579,
					5.787125113076019,
					5.155233256805516,
					5.311746513315086,
					4.836271293068644,
					4.7823661895360745,
					4.953494494963778,
					4.701318396463653,
					5.433431730068479,
					4.675396505541243,
					5.880780405775976,
					6.145075711723206,
					5.602361071629163,
					5.975476683699793,
					5.2480429962964035
				],
"Probability":1
			}
		},
		"b12": {
			"s1": {
				"Load (MW)":[
					6.447785290132809,
					5.629255184293672,
					6.454485945820659,
					6.763138901780859,
					5.297034060672152,
					5.7443419809220835,
					5.557318825569493,
					6.0684409903429275,
					5.302105664091276,
					4.572285871667732,
					5.204612435361125,
					5.582748498048319,
					5.8535825164691015,
					5.33424936746163,
					5.834217700391005,
					4.588053995021831,
					5.564546492063543,
					6.020318785087892,
					4.911619411967123,
					6.100721183915749,
					5.216634000416445,
					5.589836004922246,
					5.3810926146240945,
					5.540430946146259,
					5.179203482810486,
					6.170525991765216,
					6.192981003325744,
					5.897735524332933,
					6.909161523547151,
					6.952135915430044,
					6.916183062824908,
					6.804124602299935,
					7.100097579473076,
					6.770837347977961,
					7.442158560249366,
					7.581487467981824,
					7.046643417562158,
					7.759455430372674,
					6.913313515788964,
					7.746673183449554,
					8.809343535682949,
					8.080454472029098,
					7.927509524113393,
					8.274904433415324,
					7.472019312471872,
					8.943415980455667,
					9.111934200711083,
					9.24970294639188,
					7.345475243955069,
					8.697876626955425,
					9.654552512057094,
					10.683128260140023,
					9.719517236322249,
					10.266497156599753,
					10.181602905806933,
					8.824947898116502,
					8.701225259263586,
					8.333965629852228,
					10.200267818788067,
					10.47670737909805
				],
"Probability":1
			}
		},
		"b13": {
			"s1": {
				"Load (MW)":[
					11.527692930389042,
					14.07238604711204,
					12.63675375529471,
					11.894330791129192,
					13.62500929006708,
					12.956580997032637,
					13.527375842457452,
					12.219310695709554,
					12.83296888969069,
					11.49140356322198,
					12.5656398346826,
					12.470319485182554,
					12.088423441601451,
					11.78155689846962,
					11.199702841067053,
					12.33269352474457,
					11.571074585432365,
					12.754826763945836,
					11.930388614565738,
					12.052154031202061,
					12.599523773424714,
					12.848904549068317,
					14.20677591399361,
					11.84143742533731,
					14.307105872657639,
					12.7293428512447,
					12.158560512380891,
					14.713251693112449,
					15.210486169919248,
					14.80725525000551,
					16.736944817916726,
					15.185815374240248,
					15.009936166453377,
					15.223198635593146,
					15.400142528498218,
					16.250369028666594,
					20.409752162218446,
					13.309850793832616,
					16.869529823822543,
					17.187898677843258,
					19.50996884116143,
					19.917686738339448,
					19.561239995157607,
					20.882034859042403,
					20.69219446237161,
					18.794827809115947,
					18.068037362683686,
					20.46253384580495,
					18.960384409231025,
					20.339658142693363,
					18.808423165245927,
					22.605537388337275,
					21.771229840527198,
					19.964113148921122,
					20.142228952057952,
					21.99883994053223,
					19.31035196224659,
					17.36572299338443,
					19.855471086643785,
					19.988801050181113
				],
"Probability":1
			}
		},
		"b14": {
			"s1": {
				"Load (MW)":[
					13.7207064649713,
					15.731197099063296,
					15.378073249756891,
					16.757018284360047,
					12.426182487635835,
					14.997210400292765,
					11.85246903308116,
					15.481339973686048,
					12.833887967858365,
					13.602312453276774,
					13.51194130954872,
					11.753467818270984,
					14.095564232645508,
					13.482633311669018,
					13.054557652892973,
					13.122948611133044,
					11.682060227463117,
					11.744179163515517,
					13.572327648901123,
					11.70159368534418,
					15.334510166075843,
					13.630638864770422,
					14.100209475123155,
					13.584964935557164,
					14.191537686290406,
					17.695323098342012,
					15.002105202046101,
					15.463543838561247,
					19.0617950237303,
					15.801150856259142,
					14.947862550092587,
					16.206080026918475,
					16.185836435458032,
					19.03983020521525,
					18.38858541708324,
					20.05148475707616,
					18.894656960853187,
					14.917857668034308,
					19.112670868811783,
					20.52580004895161,
					23.04007350874195,
					18.505711678014418,
					17.75592459921198,
					21.143335027940072,
					19.52849952935982,
					20.508935837746375,
					21.255469593682214,
					23.1205793488012,
					20.51887742775401,
					20.997752066003176,
					21.4981162528915,
					21.761219963810397,
					23.78976932544116,
					22.129737860631533,
					24.66278506209141,
					23.38001534960163,
					21.456920118841282,
					22.1407908994964,
					24.7313879765558,
					28.716085115133204
				],
"Probability":1
			}
		}
	}
}