{
"Parameters": {
	"Power balance penalty ($/MW)": [10000.0, 10000.0, 10000.0, 10000.0, 10000.0, 10000.0, 10000.0, 10000.0, 10000.0, 10000.0, 10000.0, 10000.0, 10000.0, 10000.0, 10000.0, 10000.0, 10000.0, 10000.0, 10000.0, 10000.0, 10000.0, 10000.0, 10000.0, 10000.0, 10000.0, 10000.0, 10000.0, 10000.0, 10000.0, 10000.0, 10000.0, 10000.0, 10000.0, 10000.0, 10000.0, 10000.0, 10000.0, 10000.0, 10000.0, 10000.0, 10000.0, 10000.0, 10000.0, 10000.0, 10000.0, 10000.0, 10000.0, 10000.0, 10000.0, 10000.0, 10000.0, 10000.0, 10000.0, 10000.0, 10000.0, 10000.0, 10000.0, 10000.0, 10000.0, 10000.0, 10000.0, 10000.0, 10000.0, 10000.0, 10000.0, 10000.0, 10000.0, 10000.0, 10000.0, 10000.0, 10000.0, 10000.0, 10000.0, 10000.0, 10000.0, 10000.0, 10000.0, 10000.0, 10000.0, 10000.0, 10000.0, 10000.0, 10000.0, 10000.0, 10000.0, 10000.0, 10000.0, 10000.0, 10000.0, 10000.0, 10000.0, 10000.0, 10000.0, 10000.0, 10000.0, 10000.0],
	"Scenario number": 1,
	"Time horizon (h)": 3,
	"Time step (min)": 15},
	"Generators": {
		"g1": {
			"Bus": "b1",
			"Production cost curve (MW)": [16.901100444445653, 94.40345818607902, 171.90581592771244, 249.40817366934598, 326.91053141097933],
			"Production cost curve ($)": [716.7470233305867, 3465.763907745978, 6335.568940853531, 9252.345705326847, 12232.933634581022],
			"Startup costs ($)": [20559.35, 24224.12, 28727.63],
			"Startup delays (h)": [1.0, 2.0, 4.0],
			"Ramp up limit (MW)": 57.21,
			"Ramp down limit (MW)": 57.21,
			"Startup limit (MW)": 228.84,
			"Shutdown limit (MW)": 228.84,
			"Minimum uptime (h)": 1,
			"Minimum downtime (h)": 1,
			"Initial status (h)": 24,
			"Initial power (MW)": 257.74170000000004
		},
		"g2": {
			"Bus": "b2",
			"Production cost curve (MW)": [2.257203830814138, 33.5985679204243, 64.93993201003447, 96.28129609964463, 127.62266018925479],
			"Production cost curve ($)": [953.4271497797719, 2139.086577758979, 3416.0435375709003, 4856.980529832745, 6523.928912640124],
			"Startup costs ($)": [10345.29, 10498.58, 10598.13],
			"Startup delays (h)": [1.0, 2.0, 4.0],
			"Ramp up limit (MW)": 22.335,
			"Ramp down limit (MW)": 22.335,
			"Startup limit (MW)": 89.34,
			"Shutdown limit (MW)": 89.34,
			"Minimum uptime (h)": 1,
			"Minimum downtime (h)": 1,
			"Initial status (h)": -24,
			"Initial power (MW)": 0.0
		},
		"g3": {
			"Bus": "b3",
			"Production cost curve (MW)": [1.619043590917833, 21.894126410542157, 42.16920923016648, 62.444292049790796, 82.71937486941513],
			"Production cost curve ($)": [685.7745024725275, 1403.8176490424148, 2365.8595550594155, 3786.959826482599, 5342.322597393779],
			"Startup costs ($)": [4382.12, 4505.39, 4595.43],
			"Startup delays (h)": [1.0, 2.0, 4.0],
			"Ramp up limit (MW)": 14.475,
			"Ramp down limit (MW)": 14.475,
			"Startup limit (MW)": 57.9,
			"Shutdown limit (MW)": 57.9,
			"Minimum uptime (h)": 1,
			"Minimum downtime (h)": 1,
			"Initial status (h)": -24,
			"Initial power (MW)": 0.0
		},
		"g4": {
			"Bus": "b6",
			"Production cost curve (MW)": [0.8992148792351051, 22.275109867369967, 43.65100485550483, 65.02689984363968, 86.40279483177456],
			"Production cost curve ($)": [848.551414962958, 1594.5146442701787, 2520.030474640857, 3783.3547240156395, 5223.878506266689],
			"Startup costs ($)": [4274.52, 4497.57, 4827.67],
			"Startup delays (h)": [4.0, 8.0, 16.0],
			"Ramp up limit (MW)": 15.12,
			"Ramp down limit (MW)": 15.12,
			"Startup limit (MW)": 60.48,
			"Shutdown limit (MW)": 60.48,
			"Minimum uptime (h)": 4,
			"Minimum downtime (h)": 4,
			"Initial status (h)": -24,
			"Initial power (MW)": 0.0
		},
		"g5": {
			"Bus": "b8",
			"Production cost curve (MW)": [2.326914798402042, 23.12161589867012, 43.91631699893821, 64.71101809920629, 85.50571919947436],
			"Production cost curve ($)": [645.5555905711794, 1395.3861251379635, 2312.198895304892, 3543.1506774466516, 4879.427576009033],
			"Startup costs ($)": [5998.01, 6356.53, 6821.79],
			"Startup delays (h)": [1.0, 2.0, 4.0],
			"Ramp up limit (MW)": 14.9625,
			"Ramp down limit (MW)": 14.9625,
			"Startup limit (MW)": 59.85,
			"Shutdown limit (MW)": 59.85,
			"Minimum uptime (h)": 1,
			"Minimum downtime (h)": 1,
			"Initial status (h)": -24,
			"Initial power (MW)": 0.0
		}
	},
	"Transmission lines": {
		"l1": {
			"Source bus": "b1",
			"Target bus": "b2",
			"Reactance (ohms)": 0.05917000000000001,
			"Susceptance (S)": 29.496860773945063
		},
		"l2": {
			"Source bus": "b1",
			"Target bus": "b5",
			"Reactance (ohms)": 0.22304000000000002,
			"Susceptance (S)": 7.825184953346168
		},
		"l3": {
			"Source bus": "b2",
			"Target bus": "b3",
			"Reactance (ohms)": 0.19797,
			"Susceptance (S)": 8.816129979261149
		},
		"l4": {
			"Source bus": "b2",
			"Target bus": "b4",
			"Reactance (ohms)": 0.17632,
			"Susceptance (S)": 9.898645939169292
		},
		"l5": {
			"Source bus": "b2",
			"Target bus": "b5",
			"Reactance (ohms)": 0.17388,
			"Susceptance (S)": 10.037550333530765
		},
		"l6": {
			"Source bus": "b3",
			"Target bus": "b4",
			"Reactance (ohms)": 0.17103,
			"Susceptance (S)": 10.204813494675376
		},
		"l7": {
			"Source bus": "b4",
			"Target bus": "b5",
			"Reactance (ohms)": 0.04211,
			"Susceptance (S)": 41.44690695783257
		},
		"l8": {
			"Source bus": "b4",
			"Target bus": "b7",
			"Reactance (ohms)": 0.20911999999999997,
			"Susceptance (S)": 8.346065665619404
		},
		"l9": {
			"Source bus": "b4",
			"Target bus": "b9",
			"Reactance (ohms)": 0.55618,
			"Susceptance (S)": 3.1380654680037567
		},
		"l10": {
			"Source bus": "b5",
			"Target bus": "b6",
			"Reactance (ohms)": 0.25201999999999997,
			"Susceptance (S)": 6.92536009838239
		},
		"l11": {
			"Source bus": "b6",
			"Target bus": "b11",
			"Reactance (ohms)": 0.1989,
			"Susceptance (S)": 8.774908255376218
		},
		"l12": {
			"Source bus": "b6",
			"Target bus": "b12",
			"Reactance (ohms)": 0.25581,
			"Susceptance (S)": 6.8227561549365925
		},
		"l13": {
			"Source bus": "b6",
			"Target bus": "b13",
			"Reactance (ohms)": 0.13027,
			"Susceptance (S)": 13.397783465067395
		},
		"l14": {
			"Source bus": "b7",
			"Target bus": "b8",
			"Reactance (ohms)": 0.17615,
			"Susceptance (S)": 9.908198989465395
		},
		"l15": {
			"Source bus": "b7",
			"Target bus": "b9",
			"Reactance (ohms)": 0.11001,
			"Susceptance (S)": 15.865187273832648
		},
		"l16": {
			"Source bus": "b9",
			"Target bus": "b10",
			"Reactance (ohms)": 0.0845,
			"Susceptance (S)": 20.65478404727017
		},
		"l17": {
			"Source bus": "b9",
			"Target bus": "b14",
			"Reactance (ohms)": 0.27038,
			"Susceptance (S)": 6.4550974628091184
		},
		"l18": {
			"Source bus": "b10",
			"Target bus": "b11",
			"Reactance (ohms)": 0.19207,
			"Susceptance (S)": 9.08694357262628
		},
		"l19": {
			"Source bus": "b12",
			"Target bus": "b13",
			"Reactance (ohms)": 0.19988,
			"Susceptance (S)": 8.73188539120637
		},
		"l20": {
			"Source bus": "b13",
			"Target bus": "b14",
			"Reactance (ohms)": 0.34802,
			"Susceptance (S)": 5.0150257226433235
		}
	},
	"Buses": {
		"b1": {
			"s1": {
				"Load (MW)":[
					0.0,
					0.0,
					0.0,
					0.0,
					0.0,
					0.0,
					0.0,
					0.0,
					0.0,
					0.0,
					0.0,
					0.0
				],
"Probability":1
			}
		},
		"b2": {
			"s1": {
				"Load (MW)":[
					23.526101966706612,
					19.50206033263874,
					22.994139659991085,
					20.200301168687787,
					19.753360043509836,
					21.61726182825497,
					19.26130586658511,
					22.149887286537172,
					19.688985670333675,
					19.737308082637625,
					19.58060056334713,
					19.025324117149292
				],
"Probability":1
			}
		},
		"b3": {
			"s1": {
				"Load (MW)":[
					90.95161684103815,
					88.32866325462136,
					96.62371914069107,
					94.41127794604685,
					80.21090787050436,
					95.9608858961738,
					79.646637666608,
					98.46681628618741,
					88.06144364753875,
					81.24331417257629,
					87.35634047021725,
					84.05920230828318
				],
"Probability":1
			}
		},
		"b4": {
			"s1": {
				"Load (MW)":[
					48.124076594637756,
					46.594527736599545,
					46.754884361846685,
					45.260008602129844,
					42.62054976221658,
					48.25048248126905,
					44.00345549930829,
					48.537110710532424,
					39.9360163983748,
					43.821132275653824,
					41.44921287187685,
					43.72009624554235
				],
"Probability":1
			}
		},
		"b5": {
			"s1": {
				"Load (MW)":[
					7.809632093575353,
					7.25736907494257,
					7.819593798367713,
					7.356665615714605,
					7.4115800748390095,
					6.906423342156503,
					7.396105380490345,
					6.958278616099886,
					6.667197933381572,
					6.980038419217008,
					6.520361015192078,
					6.960255036254539
				],
"Probability":1
			}
		},
		"b6": {
			"s1": {
				"Load (MW)":[
					11.399647830069789,
					11.034527153876416,
					10.975225408232953,
					10.81526817885213,
					10.016800115921267,
					10.569210052108259,
					10.032737828644752,
					11.12686488967588,
					11.043954259993479,
					9.430305543510363,
					10.916514282194754,
					9.620747166872658
				],
"Probability":1
			}
		},
		"b7": {
			"s1": {
				"Load (MW)":[
					0.0,
					0.0,
					0.0,
					0.0,
					0.0,
					0.0,
					0.0,
					0.0,
					0.0,
					0.0,
					0.0,
					0.0
				],
"Probability":1
			}
		},
		"b8": {
			"s1": {
				"Load (MW)":[
					0.0,
					0.0,
					0.0,
					0.0,
					0.0,
					0.0,
					0.0,
					0.0,
					0.0,
					0.0,
					0.0,
					0.0
				],
"Probability":1
			}
		},
		"b9": {
			"s1": {
				"Load (MW)":[
					28.69843867225601,
					31.575168045104988,
					28.901099550470757,
					29.53846103731668,
					25.9217530701467,
					30.11956405020012,
					25.648233392504903,
					29.90348866134028,
					26.333617891826243,
					26.107242851779247,
					26.79870629846082,
					26.567876510292447
				],
"Probability":1
			}
		},
		"b10": {
			"s1": {
				"Load (MW)":[
					8.405706673513501,
					8.980381997025347,
					8.779626870369551,
					9.083447300149842,
					8.734648516780762,
					8.436929237642165,
					8.081863617856065,
					8.420334835816059,
					8.079884624165468,
					7.64602622379534,
					8.314351134584706,
					8.122576957433468
				],
"Probability":1
			}
		},
		"b11": {
			"s1": {
				"Load (MW)":[
					3.4348515045447883,
					3.655969476810312,
					3.4133983746923664,
					3.559254351600264,
					3.296727187799319,
					3.3857575406574822,
					3.3872765535151235,
					3.2864635992049105,
					3.271157053857228,
					2.9671532400281593,
					3.1955855215470748,
					3.0896561753027383
				],
"Probability":1
			}
		},
		"b12": {
			"s1": {
				"Load (MW)":[
					6.484303166231733,
					5.996447007974626,
					6.18155552404918,
					5.880764914904628,
					5.72548733276245,
					5.854069050592214,
					5.639391511982922,
					5.815545221007466,
					5.468445591217567,
					5.119208874632687,
					5.628167287310717,
					5.269518317967683
				],
"Probability":1
			}
		},
		"b13": {
			"s1": {
				"Load (MW)":[
					13.124350035653773,
					12.913487380670812,
					13.554068967515501,
					14.001935607835561,
					13.130343148040035,
					12.019773850651815,
					13.232531535083456,
					12.57315235973726,
					12.316232606506428,
					12.127346737363702,
					11.875076771988649,
					12.444958513958088
				],
"Probability":1
			}
		},
		"b14": {
			"s1": {
				"Load (MW)":[
					15.320179632279313,
					14.178706145203702,
					15.513304883505947,
					14.14397340259352,
					13.222113487598856,
					14.611700976718433,
					13.585896552347,
					14.669692110094012,
					13.272406010064564,
					13.218238875373682,
					13.12646105614162,
					13.343495226098945
				],
"Probability":1
			}
		}
	}
}